main.py
mseep_choose_mcp_server-0.1.14.dist-info/METADATA
mseep_choose_mcp_server-0.1.14.dist-info/WHEEL
mseep_choose_mcp_server-0.1.14.dist-info/entry_points.txt
mseep_choose_mcp_server-0.1.14.dist-info/top_level.txt
mseep_choose_mcp_server-0.1.14.dist-info/RECORD
