Metadata-Version: 2.4
Name: mseep-choose-mcp-server
Version: 0.1.14
Summary: Add your description here
Author-email: mseep <support@skydeck.ai>
Requires-Python: >=3.10.6
Requires-Dist: google-cloud-bigquery>=3.29.0
Requires-Dist: mcp[cli]>=1.3.0
